ConfNet/__init__.py
ConfNet/alias.py
ConfNet/classify.py
ConfNet/utils.py
ConfNet/walker.py
ConfNet/cluster/__init__.py
ConfNet/cluster/cluster.py
ConfNet/evaluation/__init__.py
ConfNet/evaluation/tool.py
ConfNet/geotool/__init__.py
ConfNet/geotool/geoangle.py
ConfNet/geotool/geofigures.py
ConfNet/geotool/geoplot.py
ConfNet/geotool/vec2anglemarmid.py
ConfNet/models/__init__.py
ConfNet/models/deepwalk.py
ConfNet/models/line.py
ConfNet/models/node2vec.py
ConfNet/models/sdne.py
ConfNet/models/struc2vec.py
ConfNet/models/struc2vec1.py
ConfNet/models/struc2vec2.py
ConfNet-0.0.3.dist-info/LICENSE
ConfNet-0.0.3.dist-info/METADATA
ConfNet-0.0.3.dist-info/WHEEL
ConfNet-0.0.3.dist-info/top_level.txt
ConfNet-0.0.3.dist-info/RECORD
